suspense/__init__.py
suspense/apps.py
suspense/futures.py
suspense/http.py
suspense/shortcuts.py
suspense/streaming_render.py
suspense/views.py
suspense/templates/suspense/loader.html
suspense/templates/suspense/replacer.html
suspense/templatetags/__init__.py
suspense/templatetags/suspense.py
django_suspense-1.2.0.dist-info/LICENCE
django_suspense-1.2.0.dist-info/METADATA
django_suspense-1.2.0.dist-info/WHEEL
django_suspense-1.2.0.dist-info/top_level.txt
django_suspense-1.2.0.dist-info/RECORD
