Metadata-Version: 2.1
Name: django-suspense
Version: 1.2.0
Summary: Display a fallback in templates until its children have finished loading.
Author-email: Pavel Kutsenko <zebartcoc@gmail.com>
Project-URL: Homepage, https://github.com/paqstd-dev/django-suspense
Project-URL: Bug Tracker, https://github.com/paqstd-dev/django-suspense/issues
Classifier: Environment :: Web Environment
Classifier: Framework :: Django
Classifier: Framework :: Django :: 4.2
Classifier: Framework :: Django :: 5.0
Classifier: Framework :: Django :: 5.1
Classifier: Intended Audience :: Developers
Classifier: License :: OSI Approved :: MIT License
Classifier: Programming Language :: Python
Classifier: Programming Language :: Python :: 3
Classifier: Programming Language :: Python :: 3 :: Only
Classifier: Programming Language :: Python :: 3.9
Classifier: Programming Language :: Python :: 3.10
Classifier: Programming Language :: Python :: 3.11
Classifier: Programming Language :: Python :: 3.12
Classifier: Programming Language :: Python :: 3.13
Requires-Python: >=3.9
License-File: LICENCE
